dtcv2_util/__init__.py
dtcv2_util/log_management.py
dtcv2_util/meteo_utils.py
dtcv2_util/validate_inp.py
dtcv2_util/resources/areas.json
dtcv2_util/resources/default_values.json
dtcv2_util/resources/nc_default.json
dtcv2_util/resources/options.json
dtcv2_util/resources/servers.json
dtcv2_util-1.2.0.dist-info/METADATA
dtcv2_util-1.2.0.dist-info/WHEEL
dtcv2_util-1.2.0.dist-info/top_level.txt
dtcv2_util-1.2.0.dist-info/RECORD
