Metadata-Version: 2.2
Name: dtcv2_util
Version: 1.2.0
Summary: Library for workflow management
Home-page: https://gitlab.geo3bcn.csic.es/dtgeo/dtc-v2/meteo-gfs
Author: Alejandra Guerrero - DTGEO
Author-email: aguerrero@geo3bcn.csic.es
License: MIT
Requires-Dist: datetime
Requires-Dist: xarray
Requires-Dist: requests
Requires-Dist: netcdf4
Dynamic: author
Dynamic: author-email
Dynamic: description
Dynamic: description-content-type
Dynamic: home-page
Dynamic: license
Dynamic: requires-dist
Dynamic: summary
